hamkit/uls/__about__.py
hamkit/uls/__init__.py
hamkit/uls/_common.py
hamkit/uls/_uls.py
hamkit_uls-0.0.1a3.dist-info/METADATA
hamkit_uls-0.0.1a3.dist-info/WHEEL
hamkit_uls-0.0.1a3.dist-info/licenses/LICENSE
hamkit_uls-0.0.1a3.dist-info/RECORD
