Metadata-Version: 2.3
Name: hamkit-uls
Version: 0.0.1a3
Summary: A tool for working with local copies of the FCC Universal Licensing System (ULS) database dumps (e.g., to look up information about a US call sign.)
Project-URL: Documentation, https://github.com/afourney/hamkit/blob/main/packages/uls/README.md
Project-URL: Issues, https://github.com/afourney/hamkit/issues
Project-URL: Source, https://github.com/afourney/hamkit/blob/main/packages/uls/README.md
Author-email: Adam Fourney <adam.fourney@gmail.com>
License-Expression: MIT
License-File: LICENSE
Classifier: Development Status :: 4 - Beta
Classifier: Programming Language :: Python
Classifier: Programming Language :: Python :: 3.10
Classifier: Programming Language :: Python :: 3.11
Classifier: Programming Language :: Python :: 3.12
Classifier: Programming Language :: Python :: Implementation :: CPython
Classifier: Programming Language :: Python :: Implementation :: PyPy
Requires-Python: >=3.10
Requires-Dist: requests
